sqlalchemy_sphinx/__init__.py
sqlalchemy_sphinx/cymysql.py
sqlalchemy_sphinx/dialect.py
sqlalchemy_sphinx/mysqldb.py
sqlalchemy_sphinx/pymysql.py
sqlalchemy_sphinx/utils.py
sqlalchemy_sphinx-0.9.0.dist-info/METADATA
sqlalchemy_sphinx-0.9.0.dist-info/WHEEL
sqlalchemy_sphinx-0.9.0.dist-info/entry_points.txt
sqlalchemy_sphinx-0.9.0.dist-info/top_level.txt
sqlalchemy_sphinx-0.9.0.dist-info/RECORD
