Metadata-Version: 2.1
Name: sqlalchemy-sphinx
Version: 0.9.0
Summary: SQLAlchemy extension for dealing with SphinxQL
Home-page: UNKNOWN
Author: Adriel Velazquez
Author-email: adrielvelazquez@gmail.com
License: UNKNOWN
Platform: UNKNOWN
Requires-Dist: sqlalchemy (>=1.3.0) ; python_version < "2.7"
Requires-Dist: sqlalchemy (>=1.3.0) ; python_version == "2.7" or python_version >= "3.4"
